gmocoin_client/__init__.py
gmocoin_client/client.py
gmocoin_client/errors.py
gmocoin_client/models.py
gmocoin_client-0.2.1.dist-info/licenses/LICENSE.md
gmocoin_client-0.2.1.dist-info/METADATA
gmocoin_client-0.2.1.dist-info/WHEEL
gmocoin_client-0.2.1.dist-info/top_level.txt
gmocoin_client-0.2.1.dist-info/RECORD
