Metadata-Version: 2.4
Name: gmocoin-client
Version: 0.2.1
Summary: Python API Client Library for GMO Coin / GMOコイン用のPython APIクライエントライブラリ
Project-URL: Homepage, https://gmocoin.shion.dev/
Project-URL: Documentation, https://gmocoin.shion.dev/
Project-URL: Repository, https://github.com/Shion1305/gmocoin-client
Project-URL: Issues, https://github.com/Shion1305/gmocoin-client/issues
Requires-Python: >=3.13
License-File: LICENSE.md
Requires-Dist: httpx>=0.28.1
Requires-Dist: pydantic>=2.12.2
Provides-Extra: docs
Requires-Dist: furo>=2024.8.6; extra == "docs"
Requires-Dist: sphinx>=7.4; extra == "docs"
Dynamic: license-file
